slack/manifest.toml
slack/slack.py
opsbox_slack_output-0.1.4.dist-info/LICENCE.txt
opsbox_slack_output-0.1.4.dist-info/METADATA
opsbox_slack_output-0.1.4.dist-info/WHEEL
opsbox_slack_output-0.1.4.dist-info/entry_points.txt
opsbox_slack_output-0.1.4.dist-info/top_level.txt
opsbox_slack_output-0.1.4.dist-info/RECORD
