Metadata-Version: 2.2
Name: opsbox-slack-output
Version: 0.1.4
Summary: Slack channel output for opsbox
Requires-Python: ==3.11.*
License-File: LICENCE.txt
Requires-Dist: pluggy>=1.5.0
Requires-Dist: pydantic>=2.10.2
Requires-Dist: slack-sdk>=3.34.0
Requires-Dist: opsbox-general-handler>=0.1.2
